cctp/__init__.py
cctp/cctp.py
cctp/cli.py
cctp-1.2.4.dist-info/METADATA
cctp-1.2.4.dist-info/WHEEL
cctp-1.2.4.dist-info/entry_points.txt
cctp-1.2.4.dist-info/licenses/AUTHORS.rst
cctp-1.2.4.dist-info/licenses/LICENSE
cctp-1.2.4.dist-info/RECORD
