Metadata-Version: 2.4
Name: cctp
Version: 1.2.4
Summary: Cookiecutter Template for Python.
Project-URL: Repository, https://gitee.com/gooker_young/cctp
Project-URL: Documentation, https://cctp.readthedocs.io/zh-cn/stable/
Project-URL: Issues, https://gitee.com/gooker_young/cctp/issues
Author-email: gooker_young <gooker_young@qq.com>
Maintainer-email: gooker_young <gooker_young@qq.com>
License: MIT license
License-File: AUTHORS.rst
License-File: LICENSE
Requires-Python: >=3.8
Requires-Dist: rich>=13.9.4
Requires-Dist: typer>=0.15.1
